dystore_data_collection/__init__.py
dystore_data_collection/collector.py
dystore_data_collection/compass/_utils.py
dystore_data_collection/compass/compass.py
dystore_data_collection/compass/goods.py
dystore_data_collection/home/home.py
dystore_data_collection/im/data.py
dystore_data_collection/im/im.py
dystore_data_collection/py.typed
dystore_data_collection-2.0.5.dist-info/WHEEL
dystore_data_collection-2.0.5.dist-info/METADATA
dystore_data_collection-2.0.5.dist-info/RECORD
