Metadata-Version: 2.3
Name: dystore-data-collection
Version: 2.0.5
Summary: DYStore Data Collection
Author: Martian Bugs
Requires-Dist: browser-automation-launcher>=2.0.0
Requires-Dist: tenacity>=9.1.2
Requires-Python: >=3.12
